zesty/__init__.py
zesty/actions.py
zesty/protocol.py
zesty/models/agent_report.py
zesty/models/cpu_mon.py
zesty/models/disk_mon.py
zesty/models/hf_interface.py
zesty/models/mem_mon.py
zesty/models/network_mon.py
zesty/models/overview.py
zesty.zbs_api_dev-1.0.2020.12.14.1.dist-info/METADATA
zesty.zbs_api_dev-1.0.2020.12.14.1.dist-info/WHEEL
zesty.zbs_api_dev-1.0.2020.12.14.1.dist-info/top_level.txt
zesty.zbs_api_dev-1.0.2020.12.14.1.dist-info/RECORD
