Metadata-Version: 2.1
Name: zesty.zbs-api-dev
Version: 1.0.2020.12.14.1
Summary: Zesty Disk API
Home-page: https://github.com/javatechy/dokr
Author: Zesty.co
Author-email: rnd@cloudvisor.co
License: UNKNOWN
Platform: UNKNOWN
Classifier: Programming Language :: Python :: 3
Classifier: License :: OSI Approved :: MIT License
Classifier: Operating System :: OS Independent
Requires-Dist: pytest (==6.1.1)
Requires-Dist: setuptools
Requires-Dist: wheel
Requires-Dist: twine
Requires-Dist: requests
